marko_backlinks/__init__.py
marko_backlinks/adapters/__init__.py
marko_backlinks/adapters/markdown/__init__.py
marko_backlinks/adapters/markdown/factories.py
marko_backlinks/adapters/markdown/marko_ext/__init__.py
marko_backlinks/adapters/markdown/marko_ext/elements.py
marko_backlinks/adapters/markdown/marko_extractor.py
marko_backlinks/adapters/markdown/marko_modifier.py
marko_backlinks/adapters/markdown/marko_parser.py
marko_backlinks/adapters/references_db/__init__.py
marko_backlinks/adapters/references_db/factories.py
marko_backlinks/adapters/references_db/query_builders.py
marko_backlinks/adapters/references_db/tables.py
marko_backlinks/common/__init__.py
marko_backlinks/common/exceptions.py
marko_backlinks/dto/__init__.py
marko_backlinks/dto/dto.py
marko_backlinks/entrypoints/__init__.py
marko_backlinks/entrypoints/append_linked_references.py
marko_backlinks/infrastructure/__init__.py
marko_backlinks/infrastructure/db_connection.py
marko_backlinks/interfaces/__init__.py
marko_backlinks/interfaces/modifier.py
marko_backlinks/interfaces/parser.py
marko_backlinks/interfaces/reference_extractor.py
marko_backlinks/interfaces/references_db.py
marko_backlinks/interfaces/renderer.py
marko_backlinks/py.typed
marko_backlinks/usecases/__init__.py
marko_backlinks/usecases/modify.py
marko_backlinks/usecases/parse.py
marko_backlinks/usecases/read_references.py
marko_backlinks/usecases/write.py
marko_backlinks-0.4.0.dist-info/entry_points.txt
marko_backlinks-0.4.0.dist-info/LICENSE
marko_backlinks-0.4.0.dist-info/WHEEL
marko_backlinks-0.4.0.dist-info/METADATA
marko_backlinks-0.4.0.dist-info/RECORD
